<annotation>
	<folder>images</folder>
	<filename>001098.jpg</filename>
	<path>/home/vini/Desktop/srijeda/images/001098.jpg</path>
	<source>
		<database>Unknown</database>
	</source>
	<size>
		<width>300</width>
		<height>300</height>
		<depth>3</depth>
	</size>
	<segmented>0</segmented>
	<object>
		<name>erythrocyte</name>
		<pose>Unspecified</pose>
		<truncated>0</truncated>
		<difficult>0</difficult>
		<bndbox>
			<xmin>55</xmin>
			<ymin>47</ymin>
			<xmax>98</xmax>
			<ymax>87</ymax>
		</bndbox>
	</object>
</annotation>
